pyvcdr/__init__.py
pyvcdr/pyvcdr.py
pyvcdr-0.0.9.dist-info/LICENSE
pyvcdr-0.0.9.dist-info/METADATA
pyvcdr-0.0.9.dist-info/WHEEL
pyvcdr-0.0.9.dist-info/top_level.txt
pyvcdr-0.0.9.dist-info/RECORD
