Metadata-Version: 2.1
Name: pyvcdr
Version: 0.0.9
Summary: A vcd wave file read library
Home-page: https://github.com/Jiangshan00001/pyvcdr
Author: jiangshan00000
Author-email: 710806594@qq.com
License: UNKNOWN
Platform: UNKNOWN
Classifier: Programming Language :: Python :: 3
Classifier: License :: OSI Approved :: MIT License
Classifier: Operating System :: OS Independent
